Kuat/__init__.py
tugaspypi-0.1.0.dist-info/METADATA
tugaspypi-0.1.0.dist-info/WHEEL
tugaspypi-0.1.0.dist-info/top_level.txt
tugaspypi-0.1.0.dist-info/RECORD
